pyworldtidesinfo/__init__.py
pyworldtidesinfo/__main__.py
pyworldtidesinfo/worldtidesinfo_server.py
pyworldtidesinfo-3.0.1.dist-info/LICENSE
pyworldtidesinfo-3.0.1.dist-info/METADATA
pyworldtidesinfo-3.0.1.dist-info/WHEEL
pyworldtidesinfo-3.0.1.dist-info/RECORD
