Metadata-Version: 2.1
Name: pyworldtidesinfo
Version: 3.0.1
Summary: A simple API for world tides info server
Home-page: https://github.com/jugla/pyWorldtidesinfo
License: MIT
Author: jugla
Requires-Python: >=3.7.0,<3.20
Classifier: License :: OSI Approved :: MIT License
Classifier: Programming Language :: Python
Classifier: Programming Language :: Python :: 3
Classifier: Programming Language :: Python :: 3.7
Classifier: Programming Language :: Python :: 3.8
Classifier: Programming Language :: Python :: 3.9
Classifier: Programming Language :: Python :: 3.10
Classifier: Programming Language :: Python :: 3.11
Classifier: Programming Language :: Python :: 3
Classifier: Programming Language :: Python :: Implementation :: CPython
Classifier: Programming Language :: Python :: Implementation :: PyPy
Requires-Dist: requests (>=2.22.0,<3.0.0)
Project-URL: Repository, https://github.com/jugla/pyWorldtidesinfo
